snakemake_executor_plugin_cannon/__init__.py
snakemake_executor_plugin_cannon/cannon.py
snakemake_executor_plugin_cannon/efficiency_report.py
snakemake_executor_plugin_cannon/submit_string.py
snakemake_executor_plugin_cannon/utils.py
snakemake_executor_plugin_cannon-1.8.0.post2.dist-info/METADATA
snakemake_executor_plugin_cannon-1.8.0.post2.dist-info/WHEEL
snakemake_executor_plugin_cannon-1.8.0.post2.dist-info/licenses/LICENSE
snakemake_executor_plugin_cannon-1.8.0.post2.dist-info/RECORD
